[
  {
    "name": "K9 Paw Print Rescue",
    "email": "k9pawprintrescue@gmail.com",
    "wave": 1,
    "type": "new",
    "status": "sent",
    "timestamp": "2026-06-17T16:31:09.953Z"
  },
  {
    "name": "Karma Rescue",
    "email": "info@karmarescue.org",
    "wave": 1,
    "type": "new",
    "status": "sent",
    "timestamp": "2026-06-17T16:31:12.990Z"
  },
  {
    "name": "Kate's Rescue for Animals",
    "email": "katesrescueinfo@gmail.com",
    "wave": 1,
    "type": "new",
    "status": "sent",
    "timestamp": "2026-06-17T16:31:16.022Z"
  },
  {
    "name": "Kellen Rescue",
    "email": "kellen@sti.net",
    "wave": 1,
    "type": "new",
    "status": "sent",
    "timestamp": "2026-06-17T16:31:19.054Z"
  },
  {
    "name": "Ken-Mar Rescue",
    "email": "info@kenmarrescue.org",
    "wave": 1,
    "type": "new",
    "status": "sent",
    "timestamp": "2026-06-17T16:31:22.085Z"
  },
  {
    "name": "Kimie's Kritters Pet Rescue",
    "email": "kims35@aol.com",
    "wave": 1,
    "type": "new",
    "status": "sent",
    "timestamp": "2026-06-17T16:31:25.119Z"
  },
  {
    "name": "Kinder4Rescue",
    "email": "info@kinder4rescue.org",
    "wave": 1,
    "type": "new",
    "status": "sent",
    "timestamp": "2026-06-17T16:31:28.150Z"
  },
  {
    "name": "King of Hearts Foundation",
    "email": "kingofheartsfoundation@hotmail.com",
    "wave": 1,
    "type": "new",
    "status": "sent",
    "timestamp": "2026-06-17T16:31:31.179Z"
  },
  {
    "name": "Kings County Animal Services",
    "email": "samantha.yang@co.kings.ca.us",
    "wave": 1,
    "type": "new",
    "status": "sent",
    "timestamp": "2026-06-17T16:31:34.212Z"
  },
  {
    "name": "Kings SPCA",
    "email": "savethesepups@gmail.com",
    "wave": 1,
    "type": "new",
    "status": "sent",
    "timestamp": "2026-06-17T16:31:37.244Z"
  },
  {
    "name": "Kits & Kats Rescue",
    "email": "kitskatsrescue2@gmail.com",
    "wave": 1,
    "type": "new",
    "status": "sent",
    "timestamp": "2026-06-17T16:31:40.274Z"
  },
  {
    "name": "Kitt Crusaders, Inc.",
    "email": "mary@kittcrusaders.com",
    "wave": 1,
    "type": "new",
    "status": "sent",
    "timestamp": "2026-06-17T16:31:43.306Z"
  },
  {
    "name": "Kitten Rescue",
    "email": "mail@kittenrescue.org",
    "wave": 1,
    "type": "new",
    "status": "sent",
    "timestamp": "2026-06-17T16:31:46.337Z"
  },
  {
    "name": "Kitty Bungalow Charm School for Wayward Cats",
    "email": "students@kittybungalow.org",
    "wave": 1,
    "type": "new",
    "status": "sent",
    "timestamp": "2026-06-17T16:31:49.366Z"
  },
  {
    "name": "Kitty Devore Rescue",
    "email": "petfinder@kittydevorerescue.org",
    "wave": 1,
    "type": "new",
    "status": "sent",
    "timestamp": "2026-06-17T16:31:52.397Z"
  },
  {
    "name": "Kitty Katchers",
    "email": "adoptions@kittykatchers.com",
    "wave": 1,
    "type": "new",
    "status": "sent",
    "timestamp": "2026-06-17T16:31:55.431Z"
  },
  {
    "name": "Kitty Rescue of San Diego Inc.",
    "email": "sandra.sato@navy.mil",
    "wave": 1,
    "type": "new",
    "status": "sent",
    "timestamp": "2026-06-17T16:31:58.463Z"
  },
  {
    "name": "Kribs for Kritters",
    "email": "kribsforkritters@hotmail.com",
    "wave": 1,
    "type": "new",
    "status": "sent",
    "timestamp": "2026-06-17T16:32:01.494Z"
  },
  {
    "name": "Kritter Kamp Rescue",
    "email": "kritter.kamp@yahoo.com",
    "wave": 1,
    "type": "new",
    "status": "sent",
    "timestamp": "2026-06-17T16:32:04.528Z"
  },
  {
    "name": "Kumo's Proud Tails & Whiskers, Inc.",
    "email": "kumochanmama1@gmail.com",
    "wave": 1,
    "type": "new",
    "status": "sent",
    "timestamp": "2026-06-17T16:32:07.556Z"
  }
]